SAR_Controller.v
`timescale 1ns/1ns

module SAR_Controller (
    input clk,
    input go,
    input cmp,
    output reg valid,
    output reg sample,
    output reg [7:0] result,
    output [7:0] value
);

parameter sWait = 2'b00;
parameter sSample = 2'b01;
parameter sConv = 2'b10;
parameter sDone = 2'b11;


reg [1:0] currentState; 
reg [7:0] mask; 

always @(posedge clk) begin
    if (!go) begin 
        currentState <= sWait;
        valid = 0;
        sample = 0;
    end
    
    case(currentState) 
        sWait: begin
            if (go) currentState <= sSample;
            else if (!go) currentState <= sWait;
            sample <= 0;
        end 

        sSample: begin
            if (go) begin 
                currentState <= sConv;
                mask <= 8'b10000000;
                result <= 0;
                sample <= 1;
            end
            
            if (!go) currentState <= sWait;
        end

        sConv: begin 
            sample <= 0;
            if (mask[0]) currentState <= sDone;
            if (!go) currentState <= sWait;
            if (cmp) result <= result | mask;
            mask <= mask >> 1;
        end

        sDone: begin
            sample <= 0;
            valid <= 1;
            if (!go) currentState <= sWait;
            
        end
    
    endcase

end

    assign value = result | mask;

endmodule

SAR_Controller_tb.v
`timescale 1ns/1ns

module SAR_Controller_tb();
// registers to hold inputs to circuit under test, wires for outputs 
reg clk,go;
wire valid,sample,cmp;
wire [7:0] result; 
wire [7:0] value; 

// instance controller 
SAR_Controller c(clk,go,cmp,valid, sample,result,value); 

// generate a clock with period of 20 time units 
always begin 
	#10; clk=~clk; 
end 

initial clk=0; 

// simulate analogue circuit with a digital model 
reg [7:0] hold;

always @(posedge sample) begin
    hold = 8'b01000110; 
end

assign cmp = (hold >= value); 


// monitor some signals and provide input stimuli 
initial begin 
	$monitor($time, " go=%b valid=%b result=%b sample=%b value=%b cmp=%b state=%b mask=%b", go,valid,result,sample,value,cmp,c.currentState,c.mask);
	#100; go=0; 
	#100; go=1; 
	#5000; go=0; 
	#5000; go=1; 
	#40; go=0; 
	#5000; $finish; 
end
endmodule

SAR_Controller.vcd
$date
	Mon Mar 15 23:31:40 2021
$end
$version
	Icarus Verilog
$end
$timescale
	1ns
$end
$scope module SAR_Controller_tb $end
$var wire 8 ! value [7:0] $end
$var wire 1 " valid $end
$var wire 1 # sample $end
$var wire 8 $ result [7:0] $end
$var wire 1 % cmp $end
$var reg 1 & clk $end
$var reg 1 ' go $end
$var reg 8 ( hold [7:0] $end
$scope module c $end
$var wire 1 & clk $end
$var wire 1 % cmp $end
$var wire 1 ' go $end
$var wire 8 ) value [7:0] $end
$var reg 2 * currentState [1:0] $end
$var reg 8 + mask [7:0] $end
$var reg 8 , result [7:0] $end
$var reg 1 # sample $end
$var reg 1 " valid $end
$upscope $end
$upscope $end
$enddefinitions $end
#0
$dumpvars
bx ,
bx +
bx *
bx )
bx (
x'
0&
x%
bx $
x#
x"
bx !
$end
#10
1&
#20
0&
#30
1&
#40
0&
#50
1&
#60
0&
#70
1&
#80
0&
#90
1&
#100
0&
0'
#110
b0 *
0#
0"
1&
#120
0&
#130
b1 *
1&
#140
0&
#150
0%
b1000110 (
b10000000 !
b10000000 )
1#
b0 $
b0 ,
b10000000 +
b10 *
1&
#160
0&
#170
1%
b1000000 !
b1000000 )
b1000000 +
b0 *
0#
1&
#180
0&
#190
b1 *
1&
#200
0&
1'
#210
0%
b10000000 !
b10000000 )
1#
b10000000 +
b10 *
1&
#220
0&
#230
1%
b1000000 !
b1000000 )
b1000000 +
0#
1&
#240
0&
#250
0%
b1100000 !
b1100000 )
b100000 +
b1000000 $
b1000000 ,
1&
#260
0&
#270
b1010000 !
b1010000 )
b10000 +
1&
#280
0&
#290
b1001000 !
b1001000 )
b1000 +
1&
#300
0&
#310
1%
b1000100 !
b1000100 )
b100 +
1&
#320
0&
#330
b1000110 !
b1000110 )
b10 +
b1000100 $
b1000100 ,
1&
#340
0&
#350
0%
b1000111 !
b1000111 )
b1 +
b1000110 $
b1000110 ,
1&
#360
0&
#370
1%
b1000110 !
b1000110 )
b0 +
b11 *
1&
#380
0&
#390
1"
1&
